{
  "gitSyncId": "67faa44513b8b524c099f316_27a950b0-feb7-4563-b188-6f9d85c08ef8",
  "id": "ListagemEmpresas_tarefasJS.podeSolicitar",
  "pluginId": "js-plugin",
  "pluginType": "JS",
  "unpublishedAction": {
    "actionConfiguration": {
      "encodeParamsToggle": true,
      "jsArguments": [],
      "paginationType": "NONE",
      "timeoutInMillisecond": 10000
    },
    "collectionId": "ListagemEmpresas_tarefasJS",
    "confirmBeforeExecute": false,
    "datasource": {
      "isAutoGenerated": false,
      "name": "UNUSED_DATASOURCE",
      "pluginId": "js-plugin"
    },
    "dynamicBindingPathList": [
      {
        "key": "body"
      }
    ],
    "executeOnLoad": false,
    "fullyQualifiedName": "tarefasJS.podeSolicitar",
    "name": "podeSolicitar",
    "pageId": "ListagemEmpresas",
    "userSetOnLoad": false
  }
}